.editorconfig
.gitignore
.gitlab-ci.yml
README.rst
changelog.rst
publish.settings.sh
publish.sh
pyproject.toml
todo.rst
tsconfig.json
.idea/modules.xml
.idea/peek-abstract-chunked-index.iml
.idea/inspectionProfiles/Project_Default.xml
.idea/inspectionProfiles/profiles_settings.xml
peek_abstract_chunked_index/PlatformDependencyTest.py
peek_abstract_chunked_index/__init__.py
peek_abstract_chunked_index.egg-info/PKG-INFO
peek_abstract_chunked_index.egg-info/SOURCES.txt
peek_abstract_chunked_index.egg-info/dependency_links.txt
peek_abstract_chunked_index.egg-info/requires.txt
peek_abstract_chunked_index.egg-info/top_level.txt
peek_abstract_chunked_index/plugin-module/ChunkedIndexModelSetTuple.ts
peek_abstract_chunked_index/plugin-module/ChunkedIndexService.ts
peek_abstract_chunked_index/plugin-module/ChunkedTuple.ts
peek_abstract_chunked_index/plugin-module/ChunkedTypeTuple.ts
peek_abstract_chunked_index/plugin-module/index.ts
peek_abstract_chunked_index/plugin-module/_private/PluginNames.ts
peek_abstract_chunked_index/plugin-module/_private/index-blueprint-tuple.service.ts
peek_abstract_chunked_index/plugin-module/_private/index.ts
peek_abstract_chunked_index/plugin-module/_private/admin/ChunkedIndexServerStatusTuple.ts
peek_abstract_chunked_index/plugin-module/_private/chunked-index-loader/ChunkedIndexEncodedChunkTuple.ts
peek_abstract_chunked_index/plugin-module/_private/chunked-index-loader/ChunkedIndexLoaderService.ts
peek_abstract_chunked_index/plugin-module/_private/chunked-index-loader/ChunkedIndexUpdateDateTuple.ts
peek_abstract_chunked_index/plugin-module/_private/chunked-index-loader/index.ts
peek_abstract_chunked_index/plugin-module/_private/tuples/OfflineConfigTuple.ts
peek_abstract_chunked_index/private/__init__.py
peek_abstract_chunked_index/private/alembic.ini
peek_abstract_chunked_index/private/client/__init__.py
peek_abstract_chunked_index/private/client/controller/ACICacheControllerABC.py
peek_abstract_chunked_index/private/client/controller/ACICacheControllerLoadFromLogicMixin.py
peek_abstract_chunked_index/private/client/controller/ACICacheControllerNotifyMixin.py
peek_abstract_chunked_index/private/client/controller/ACICacheControllerOfflineIndexMixin.py
