Metadata-Version: 2.4
Name: peek-abstract-chunked-index
Version: 5.0.4
Summary: Peek Abstract Chunked Index - blueprint for how the Peek indexed data with offline support works
Author-email: Synerty <contact@synerty.com>
Project-URL: Homepage, https://github.com/Synerty/peek-abstract-chunked-index
Keywords: Peek,Python,Platform,synerty
Requires-Dist: peek-plugin-base==5.0.4
